{
    "id": "1484",
    "標題": "越南出口「 CO SO THANG PHAT酥心糖」檢出黃麴毒素含量不符規定",
    "圖片": "https:\/\/consumer.fda.gov.tw\/DownloadMethod\/ashx\/showImage.ashx?type=unsafefood&id=1484",
    "進口商(公司名稱)": "金門行銷有限公司",
    "進口商(公司地址)": "台北縣中和市民德路290巷10號1樓",
    "貨品分類號列": "1704.90.00.10-6",
    "檢驗方法": "",
    "不合格原因暨檢出量詳細說明": "檢出含總黃麴毒素20 ppb，超出限量標準",
    "法規限量標準": "10 ppb",
    "製造廠或出口商名稱": "",
    "製造商代碼": "",
    "牌名": "CO SO THANG PHAT",
    "重量": "3612\r\n 公斤",
    "處置情形": "1.案內不合格產品未進口我國。\r\n2.依規定，報驗廠商得於15日內申請複驗1次。",
    "發布日期": "2010\/01\/27",
    "報驗受理日期": "2010\/01\/11"
}