{
    "id": "1488",
    "標題": "越南出口「HDP,BAO LOC,LAM DONG紅茶」檢出殘留農藥含量不符規定",
    "圖片": "https:\/\/consumer.fda.gov.tw\/DownloadMethod\/ashx\/showImage.ashx?type=unsafefood&id=1488",
    "進口商(公司名稱)": "亞東製茶廠有限公司",
    "進口商(公司地址)": "台北市重慶北路2段80巷2號2樓",
    "貨品分類號列": "0902.40.90.00-2",
    "檢驗方法": "",
    "不合格原因暨檢出量詳細說明": "檢出芬普尼0.07ppm",
    "法規限量標準": "不得檢出",
    "製造廠或出口商名稱": "",
    "製造商代碼": "",
    "牌名": "HDP,BAO LOC,LAM DONG",
    "重量": "5,000\r\n 公斤",
    "處置情形": "1.案內不合格產品未進入我國。\r\n2.依規定，報驗廠商得於15日內申請複驗1次。",
    "發布日期": "2010\/02\/03",
    "報驗受理日期": "2010\/01\/23"
}