{
    "id": "2273",
    "標題": "印尼出口「PT. PC UTAMA MANDIRI冷凍蝦蛄」檢出重金屬含量不符規定",
    "圖片": "https:\/\/consumer.fda.gov.tw\/DownloadMethod\/ashx\/showImage.ashx?type=unsafefood&id=2273",
    "進口商(公司名稱)": "江哲有限公司",
    "進口商(公司地址)": "高雄巿左營區自由二路３３２號",
    "貨品分類號列": "0306.19.00.00-0",
    "檢驗方法": "",
    "不合格原因暨檢出量詳細說明": "本案經檢出重金屬鎘0.6ppm",
    "法規限量標準": "依甲殼類重金屬鎘限量標準為0.5 ppm",
    "製造廠或出口商名稱": "PT. PC UTAMA MANDIRI",
    "製造商代碼": "",
    "牌名": "PT. PC UTAMA MANDIRI",
    "重量": "1,983.6 公斤",
    "處置情形": "案內不合格商品依規定退運或銷毀。",
    "發布日期": "2012\/08\/08",
    "報驗受理日期": "2012\/07\/12"
}