{
    "id": "2430",
    "標題": "印度出口「JKT ENTERPRISES PVT,LTD.\t芝麻」檢出殘留農藥含量不符規定",
    "圖片": "https:\/\/consumer.fda.gov.tw\/DownloadMethod\/ashx\/showImage.ashx?type=unsafefood&id=2430",
    "進口商(公司名稱)": "順邁貿易有限公司",
    "進口商(公司地址)": "高雄巿中正一路161號2樓",
    "貨品分類號列": "1207.40.00.00-1",
    "檢驗方法": "",
    "不合格原因暨檢出量詳細說明": "檢出殘留農藥馬拉松0.05 ppm",
    "法規限量標準": "依據「殘留農藥安全容許量標準」農藥馬拉松限量0.01 ppm，本案不符合食品衛生管理法第11條規定。",
    "製造廠或出口商名稱": "JKT ENTERPRISES PVT,LTD.",
    "製造商代碼": "",
    "牌名": "JKT ENTERPRISES PVT,LTD.",
    "重量": "95000  公斤",
    "處置情形": "案內不合格商品依規定退運或銷毀。",
    "發布日期": "2012\/12\/25",
    "報驗受理日期": "2012\/12\/03"
}