{
    "id": "2488",
    "標題": "中國大陸出口「HC調製化核橄欖」檢出甜味劑含量不符規定",
    "圖片": "https:\/\/consumer.fda.gov.tw\/DownloadMethod\/ashx\/showImage.ashx?type=unsafefood&id=2488",
    "進口商(公司名稱)": "時信財企業有限公司",
    "進口商(公司地址)": "台北市中正區中華路1段59號7樓",
    "貨品分類號列": "2006.00.23.00-3",
    "檢驗方法": "",
    "不合格原因暨檢出量詳細說明": "檢出環己基(代)磺醯銨酸鹽1.4 g\/kg",
    "法規限量標準": "依據「食品添加物使用範圍及限量暨規格標準」，環己基(代)磺醯銨酸在鹽瓜子及蜜餞類限量為1.0 g\/kg，本案不符合食品衛生管理法第12條規定。",
    "製造廠或出口商名稱": "COMBO TRADING CO.",
    "製造商代碼": "",
    "牌名": "HC",
    "重量": "1,836 公斤",
    "處置情形": "案內不合格商品依規定退運或銷毀。",
    "發布日期": "2013\/02\/05",
    "報驗受理日期": "2013\/01\/05"
}