{
    "id": "3088",
    "標題": "日本出口「DATWA天然黑色NO.1(HI&#160;BLACK&#160;NO.1)」檢出重金屬含量不符規定",
    "圖片": "https:\/\/consumer.fda.gov.tw\/DownloadMethod\/ashx\/showImage.ashx?type=unsafefood&id=3088",
    "進口商(公司名稱)": "振誠貿易股份有限公司",
    "進口商(公司地址)": "台北市中正區師大路181號",
    "貨品分類號列": "3203.00.19.00-8",
    "檢驗方法": "",
    "不合格原因暨檢出量詳細說明": "檢出砷5.53 ppm",
    "法規限量標準": "依據「食用天然色素衛生標準」，砷(以As計)限量為3 ppm，本案不符合食品衛生管理法第17條規定。",
    "製造廠或出口商名稱": "DAIWA DYESTUFF MFG CO.,LTD",
    "製造商代碼": "埼玉",
    "牌名": "DATWA",
    "重量": "30   公斤",
    "處置情形": "案內不合格商品依規定退運或銷毀。",
    "發布日期": "2014\/01\/29",
    "報驗受理日期": "2013\/12\/24"
}