{
    "id": "3239",
    "標題": "中國大陸出口「永川豆豉(永川豆豉)」檢出防腐劑含量不符規定",
    "圖片": "https:\/\/consumer.fda.gov.tw\/DownloadMethod\/ashx\/showImage.ashx?type=unsafefood&id=3239",
    "進口商(公司名稱)": "圓融國際有限公司",
    "進口商(公司地址)": "新北市三峽區大同路67號1樓",
    "貨品分類號列": "2103.90.90.90.5",
    "檢驗方法": "",
    "不合格原因暨檢出量詳細說明": "檢出防腐劑(以去水醋酸計0.11 g\/kg)",
    "法規限量標準": "依據「食品添加物使用範圍及限量暨規格標準」，案內產品非表列准用食品範圍，本案不符合食品安全衛生管理法第18條規定。",
    "製造廠或出口商名稱": "重慶市永川安君豆豉食品有限公司",
    "製造商代碼": "",
    "牌名": "",
    "重量": "750   公斤",
    "處置情形": "案內不合格商品依規定退運或銷毀。",
    "發布日期": "2014\/04\/30",
    "報驗受理日期": "2014\/04\/02"
}