{
    "id": "3613",
    "標題": "日本出口「LONG&#160;DE&#160;TRADE&#160;CO.,LTD紫蘇葉(OOBA&#160;(TOYOHASHI))」檢出殘留農藥含量不符規定",
    "圖片": "https:\/\/consumer.fda.gov.tw\/DownloadMethod\/ashx\/showImage.ashx?type=unsafefood&id=3613",
    "進口商(公司名稱)": "力川貿易有限公司",
    "進口商(公司地址)": "台北市中山區農安街32號7樓之2",
    "貨品分類號列": "0709.99.90.90.8",
    "檢驗方法": "",
    "不合格原因暨檢出量詳細說明": "檢出殘留農藥剋安勃0.6 ppm",
    "法規限量標準": "依據「農藥殘留容許量標準」，農藥剋安勃限值為0.01 ppm，本案不符合食品安全衛生管理法第15條規定。",
    "製造廠或出口商名稱": "LONG&#160;DE&#160;TRADE&#160;CO.,LTD",
    "製造商代碼": "愛知",
    "牌名": "LONG&#160;DE&#160;TRADE&#160;CO.,LTD",
    "重量": "6   公斤",
    "處置情形": "案內不符合商品依規定退運或銷毀。",
    "發布日期": "2014\/10\/14",
    "報驗受理日期": "2014\/09\/18"
}