{
    "id": "3633",
    "標題": "日本出口「LONG DE TRADE CO., LTD.生鮮冷藏蔥(FRESH YAKKONEGI)」檢出殘留農藥含量不符規定",
    "圖片": "https:\/\/consumer.fda.gov.tw\/DownloadMethod\/ashx\/showImage.ashx?type=unsafefood&id=3633",
    "進口商(公司名稱)": "富帆商店",
    "進口商(公司地址)": "新北市中和區建康路252號1樓",
    "貨品分類號列": "0703.90.00.00.1",
    "檢驗方法": "",
    "不合格原因暨檢出量詳細說明": "檢出殘留農藥脫芬瑞0.02 ppm",
    "法規限量標準": "依據「農藥殘留容許量標準」，農藥脫芬瑞限值為0.01 ppm，本案不符合食品安全衛生管理法第15條規定。",
    "製造廠或出口商名稱": "LONG DE TRADE CO., LTD.",
    "製造商代碼": "高知",
    "牌名": "LONG DE TRADE CO., LTD.",
    "重量": "5.85  公斤",
    "處置情形": "案內不符合商品依規定退運或銷毀。",
    "發布日期": "2014\/10\/21",
    "報驗受理日期": "2014\/09\/26"
}