{
    "id": "3900",
    "標題": "印度出口「HOMECHEF印度純椰子油(20 CTN COCONUT OIL)」檢出真菌毒素含量不符規定",
    "圖片": "https:\/\/consumer.fda.gov.tw\/DownloadMethod\/ashx\/showImage.ashx?type=unsafefood&id=3900",
    "進口商(公司名稱)": "駱洋股份有限公司",
    "進口商(公司地址)": "臺北市大安區仁愛路三段143巷23號6樓",
    "貨品分類號列": "1513.19.00.00.7",
    "檢驗方法": "衛生福利部食品藥物管理署102.09.06部授食字第1021950329號食品中黴菌毒素檢驗方法-黃麴毒素之檢驗",
    "不合格原因暨檢出量詳細說明": "檢出總黃麴毒素13 ppb",
    "法規限量標準": "依據「食品中真菌毒素限量標準」，黃麴毒素限量為10 ppb，本案不符合食品安全衛生管理法第17條規定。",
    "製造廠或出口商名稱": "FINEDAY FOODS, COCHIN, KERALA, INDIA.",
    "製造商代碼": "",
    "牌名": "HOMECHEF",
    "重量": "240  公斤",
    "處置情形": "案內不符合商品依規定退運或銷毀。",
    "發布日期": "2015\/01\/27",
    "報驗受理日期": "2014\/12\/23"
}