{
    "id": "3982",
    "標題": "美國出口「ALL CHOCOLATE綜合巧克力袋(999984 ALL CHOCOLATE INTL  BAG)」檢出含非法定著色劑",
    "圖片": "https:\/\/consumer.fda.gov.tw\/DownloadMethod\/ashx\/showImage.ashx?type=unsafefood&id=3982",
    "進口商(公司名稱)": "好市多股份有限公司",
    "進口商(公司地址)": "高雄市前鎮區中華五路656號1樓",
    "貨品分類號列": "1806.31.00.00-7",
    "檢驗方法": "衛生福利部食品藥物管理署102.09.06部授食字第1021950329號公告食品中著色劑之檢驗法",
    "不合格原因暨檢出量詳細說明": "檢出非法定可使用色素",
    "法規限量標準": "本案不符合食品安全衛生管理法第15條規定。",
    "製造廠或出口商名稱": "CWI PACKAGING (HERSHEY,MARS,NESTLE)",
    "製造商代碼": "",
    "牌名": "ALL CHOCOLATE",
    "重量": "2,754  公斤",
    "處置情形": "案內不符合商品依規定退運或銷毀。",
    "發布日期": "2015\/03\/04",
    "報驗受理日期": "2014\/12\/23"
}